Flask_Environment-0.3.1.dist-info/DESCRIPTION.rst
Flask_Environment-0.3.1.dist-info/METADATA
Flask_Environment-0.3.1.dist-info/RECORD
Flask_Environment-0.3.1.dist-info/WHEEL
Flask_Environment-0.3.1.dist-info/metadata.json
Flask_Environment-0.3.1.dist-info/top_level.txt
Flask_Environment-0.3.1.dist-info/zip-safe
flask_environment/__init__.py
